sgmail/__init__.py
sgmail/sgmail.py
sgmail-0.0.6.dist-info/LICENSE
sgmail-0.0.6.dist-info/METADATA
sgmail-0.0.6.dist-info/WHEEL
sgmail-0.0.6.dist-info/top_level.txt
sgmail-0.0.6.dist-info/RECORD
